my_sky_scanner/__init__.py
my_sky_scanner/sky.py
my_sky_scanner/trip.py
my_sky_scanner-0.1.4.dist-info/LICENSE
my_sky_scanner-0.1.4.dist-info/WHEEL
my_sky_scanner-0.1.4.dist-info/METADATA
my_sky_scanner-0.1.4.dist-info/RECORD
