Metadata-Version: 2.1
Name: my_sky_scanner
Version: 0.1.4
Summary: my_sky_scanner
Author-email: Simone Sangeniti <sangeniti.ss@gmail.com>
Requires-Python: >=3.9
Classifier: License :: OSI Approved :: MIT License
Requires-Dist: requests >=2.27.0
Requires-Dist: pytz
Requires-Dist: pytest ; extra == "test"
Project-URL: Documentation, https://github.com/Sn4k3ss/mySkyScanner_module
Project-URL: Home, https://github.com/Sn4k3ss/mySkyScanner_module
Project-URL: Source, https://github.com/Sn4k3ss/mySkyScanner_module
Provides-Extra: test
